{"desc":"Vframe类","alias":"Vframe","id":482,"methods":[{"type":"Vframe","desc":"获取根vframe","alias":"Vframe.root","id":496,"isStatic":true,"memberOf":"Vframe","returns":[{"title":"return","type":"Vframe"}],"isPrivate":true,"isa":"FUNCTION","_name":"root","_params":[{"title":"param","desc":"vom对象","type":"VOM","name":"vom"},{"title":"param","name":"refLoc"}]},{"desc":"加载对应的view","alias":"Vframe#mountView","id":503,"memberOf":"Vframe","isa":"FUNCTION","_name":"mountView","_params":[{"title":"param","desc":"形如:app/views/home?type=1&page=2 这样的名称","type":"String","name":"viewPath"},{"title":"param","desc":"view在调用init时传递的参数","type":"Object|Null","name":"viewInitParams"},{"title":"param","desc":"view加载完成并触发inited事件时的回调","type":"Function","name":"callback"}]},{"desc":"销毁对应的view","alias":"Vframe#unmountView","id":530,"memberOf":"Vframe","isa":"FUNCTION","_name":"unmountView"},{"type":"Vframe","desc":"加载vframe","alias":"Vframe#mountVframe","id":536,"memberOf":"Vframe","returns":[{"title":"return","desc":"vframe对象","type":"Vframe"}],"isa":"FUNCTION","_name":"mountVframe","_params":[{"title":"param","desc":"节点id","type":"String","name":"id"},{"title":"param","desc":"view路径","type":"String","name":"viewPath"},{"title":"param","desc":"传递给view init方法的参数","type":"Object","name":"viewInitParams"},{"title":"param","desc":"是否自动渲染","type":"Boolean","name":"autoMount"}],"example":[{"title":"example","desc":"//html\r<div id=\"magix_vf_defer\"></div>\r//js\rview.owner.mountVframe('magix_vf_defer','app/views/list',{page:2})\r//注意：动态向某个节点渲染view时，该节点无须是vframe标签"}]},{"desc":"加载当前view下面的子view，因为view的持有对象是vframe，所以是加载vframes","alias":"Vframe#mountZoneVframes","id":542,"memberOf":"Vframe","isa":"FUNCTION","_name":"mountZoneVframes","_params":[{"title":"param","desc":"节点对象或id","type":"zoneId","name":"HTMLElement|String"},{"title":"param","name":"viewInitParams"},{"title":"param","name":"autoMount"}]},{"desc":"销毁vframe","alias":"Vframe#unmountVframe","id":561,"memberOf":"Vframe","isa":"FUNCTION","_name":"unmountVframe","_params":[{"title":"param","desc":"节点id","type":"String","name":"id","isOptional":true}]},{"desc":"销毁某个区域下面的所有子vframes","alias":"Vframe#unmountZoneVframes","id":568,"memberOf":"Vframe","isa":"FUNCTION","_name":"unmountZoneVframes","_params":[{"title":"param","desc":"节点对象或id","type":"HTMLElement|String","name":"zoneId","isOptional":true}]},{"type":"Object","desc":"调用view中的方法","alias":"Vframe#invokeView","id":580,"memberOf":"Vframe","returns":[{"title":"return","type":"Object"}],"isa":"FUNCTION","_name":"invokeView","_params":[{"title":"param","desc":"方法名","type":"String","name":"methodName"},{"title":"param","desc":"向方法传递的参数","type":"Object","name":"args1,args2","isOptional":true}]},{"desc":"通知所有的子view创建完成","alias":"Vframe#cCreated","id":586,"memberOf":"Vframe","isPrivate":true,"isa":"FUNCTION","_name":"cCreated","_params":[{"title":"param","name":"e"}]},{"desc":"通知子vframe有变化","alias":"Vframe#cAlter","id":593,"memberOf":"Vframe","isPrivate":true,"isa":"FUNCTION","_name":"cAlter","_params":[{"title":"param","name":"e"}]},{"desc":"通知当前vframe，地址栏发生变化","alias":"Vframe#locChged","id":602,"memberOf":"Vframe","isPrivate":true,"isa":"FUNCTION","_name":"locChged","_params":[{"title":"param","desc":"window.location.href解析出来的对象","type":"Object","name":"loc"},{"title":"param","desc":"包含有哪些变化的对象","type":"Object","name":"chged"}],"properties":[{"isInner":true,"desc":"事件对象","alias":"Vframe#locChged-args","id":606,"methods":[{"desc":"阻止向所有的子view传递","alias":"Vframe#locChged-args.prevent","id":609,"isStatic":true,"memberOf":"Vframe#locChged-args","isa":"FUNCTION","_name":"prevent"},{"desc":"向特定的子view传递","alias":"Vframe#locChged-args.toChildren","id":611,"isStatic":true,"memberOf":"Vframe#locChged-args","isa":"FUNCTION","_name":"toChildren","_params":[{"title":"param","desc":"子view数组","type":"Array","name":"c"}]}],"memberOf":"Vframe#locChged","isa":"OBJECT","_name":"args"}]},{"desc":"绑定事件","alias":"Vframe#on","id":1244,"memberOf":"Vframe","isa":"FUNCTION","_name":"on","_params":[{"title":"param","desc":"事件名称","type":"String","name":"name"},{"title":"param","desc":"事件回调","type":"Function","name":"fn"},{"title":"param","desc":"事件监听插入的位置或触发后是否移除监听","type":"Interger|Boolean","name":"insertOrRemove"}],"example":[{"title":"example","desc":"var T=Magix.mix({},Event);\rT.on('done',function(e){\r\r});\r\rT.on('done',function(e){\r\r},0)//监听插入到开始位置\r\rT.on('done',function(e){\r\r},true)//触发后即删除该监听\r\rT.fire('done',{\r    data:'test'\r})"}]},{"desc":"触发事件","alias":"Vframe#fire","id":1245,"memberOf":"Vframe","isa":"FUNCTION","_name":"fire","_params":[{"title":"param","desc":"事件名称","type":"String","name":"name"},{"title":"param","desc":"事件对象","type":"Object","name":"data"},{"title":"param","desc":"事件触发完成后是否移除这个事件的所有监听","type":"Boolean","name":"remove"},{"title":"param","desc":"是否从后向前触发事件的监听列表","type":"Boolean","name":"lastToFirst"}]},{"desc":"解除事件绑定","alias":"Vframe#un","id":1246,"memberOf":"Vframe","isa":"FUNCTION","_name":"un","_params":[{"title":"param","desc":"事件名称","type":"String","name":"name"},{"title":"param","desc":"事件回调","type":"Function","name":"fn"}]}],"events":[{"desc":"view初始化完成后触发，由于vframe可以渲染不同的view，也就是可以通过mountView来渲染其它view，所以viewInited可能触发多次","alias":"Vframe#event:viewInited","id":620,"memberOf":"Vframe","isEvent":true,"isa":"FUNCTION","_name":"viewInited","_params":[{"title":"param","type":"Object","name":"e"}]},{"desc":"view卸载时触发，由于vframe可以渲染不同的view，因此该事件可能被触发多次","alias":"Vframe#event:viewUnmounted","id":621,"memberOf":"Vframe","isEvent":true,"isa":"FUNCTION","_name":"viewUnmounted"},{"desc":"子孙view修改时触发","alias":"Vframe#event:alter","id":622,"memberOf":"Vframe","isEvent":true,"isa":"FUNCTION","_name":"alter","_params":[{"title":"param","type":"Object","name":"e"}]},{"desc":"子孙view创建完成时触发","alias":"Vframe#event:created","id":623,"memberOf":"Vframe","isEvent":true,"isa":"FUNCTION","_name":"created","_params":[{"title":"param","type":"Object","name":"e"}]},{"desc":"vframe销毁时触发","alias":"Vframe#event:destroy","id":624,"memberOf":"Vframe","isEvent":true,"isa":"FUNCTION","_name":"destroy"}],"isa":"CONSTRUCTOR","_name":"Vframe","_params":[{"title":"param","desc":"vframe id","type":"String","name":"id"}],"inherits":[{"alias":"Event.on","as":"Vframe#on"},{"alias":"Event.fire","as":"Vframe#fire"},{"alias":"Event.un","as":"Vframe#un"}],"properties":[{"type":"String","desc":"vframe id","alias":"Vframe#id","id":483,"memberOf":"Vframe","isa":"OBJECT","_name":"id"},{"type":"View","desc":"view对象","alias":"Vframe#view","id":484,"memberOf":"Vframe","isa":"OBJECT","_name":"view"},{"type":"VOM","desc":"VOM对象","alias":"Vframe#owner","id":485,"memberOf":"Vframe","isa":"OBJECT","_name":"owner"},{"type":"Boolean","desc":"view是否完成初始化，即view的inited事件有没有派发","alias":"Vframe#viewInited","id":486,"memberOf":"Vframe","isa":"OBJECT","_name":"viewInited"}]}